tests/__init__.py
tests/conftest.py
tests/test_microsoft_stt.py
tests/test_multilanguage.py
tests/test_transcribe.py
wyoming_microsoft_stt/__init__.py
wyoming_microsoft_stt/__main__.py
wyoming_microsoft_stt/download.py
wyoming_microsoft_stt/handler.py
wyoming_microsoft_stt/languages.json
wyoming_microsoft_stt/microsoft_stt.py
wyoming_microsoft_stt/version.py
wyoming_microsoft_stt-1.3.7.dist-info/METADATA
wyoming_microsoft_stt-1.3.7.dist-info/WHEEL
wyoming_microsoft_stt-1.3.7.dist-info/top_level.txt
wyoming_microsoft_stt-1.3.7.dist-info/RECORD
