Metadata-Version: 2.4
Name: wyoming-microsoft-stt
Version: 1.3.7
Summary: Add your description here
Home-page: https://github.com/hugobloem/wyoming-microsoft-stt
Author: Hugo Bloem
Author-email: 
Requires-Python: >=3.13
Requires-Dist: azure-cognitiveservices-speech>=1.46.0
Requires-Dist: pydantic>=2.11.7
Requires-Dist: wyoming>=1.7.2
Dynamic: author
Dynamic: home-page
